vissccnet/GUI.py
vissccnet/__init__.py
vissccnet/dataloader_gui.py
vissccnet/freq_response.py
vissccnet/models.py
vissccnet/scheme_var.py
vissccnet/test.py
vissccnet/train_test.py
vissccnet/variable.py
vissccnet/datautil/__init__.py
vissccnet/datautil/xy.py
vissccnet-0.2.5.dist-info/LICENSE
vissccnet-0.2.5.dist-info/METADATA
vissccnet-0.2.5.dist-info/WHEEL
vissccnet-0.2.5.dist-info/top_level.txt
vissccnet-0.2.5.dist-info/RECORD
