Metadata-Version: 2.1
Name: vissccnet
Version: 0.2.5
Summary: A CNN model training and weight visualization GUI
Home-page: https://github.com/skywalkerylh/visSCCNet
Author: Ya-Lin Huang
Author-email: bai06hua28lin.bt06@nctu.edu.tw
License: UNKNOWN
Keywords: eeg deep-learning brain-state-decoding
Platform: UNKNOWN
Classifier: Intended Audience :: Developers
Classifier: Intended Audience :: Science/Research
Classifier: Topic :: Software Development :: Build Tools
Classifier: Topic :: Scientific/Engineering :: Artificial Intelligence
Classifier: License :: OSI Approved :: GNU General Public License v3 (GPLv3)
Classifier: Programming Language :: Python :: 3.7
License-File: LICENSE
Requires-Dist: mne
Requires-Dist: numpy
Requires-Dist: scipy
Requires-Dist: matplotlib
